openfisca_france_local/__init__.py
openfisca_france_local/aides_jeunes_reform.py
openfisca_france_local/convert_benefit_conditions_to_parameters.py
openfisca_france_local/epci_test_factory.py
openfisca_france_local/epcicom2020.xlsx
openfisca_france_local/fsl.py
openfisca_france_local/logement_social.py
openfisca_france_local/simulation_reform.py
openfisca_france_local/test_dispositif.py
openfisca_france_local/communes/alfortville/eligibilite.py
openfisca_france_local/communes/alfortville/noel_enfants.py
openfisca_france_local/communes/antony/antony_aide_depart_sejour_adapte.py
openfisca_france_local/communes/antony/antony_bourse_communale.py
openfisca_france_local/communes/antony/antony_bourse_conservatoire.py
openfisca_france_local/communes/antony/antony_bourse_famille_nombreuse.py
openfisca_france_local/communes/antony/antony_noel_pour_tous.py
openfisca_france_local/communes/antony/base_ressources.py
openfisca_france_local/communes/antony/eligibilite.py
openfisca_france_local/communes/cambrai/aide_permis.py
openfisca_france_local/communes/carcassonne/aide_permis.py
openfisca_france_local/communes/carcassonne/eligibilite.py
openfisca_france_local/communes/illkirch_graffenstaden/base.py
openfisca_france_local/communes/iwuy/aide_permis.py
openfisca_france_local/communes/le_cateau/aide_permis.py
openfisca_france_local/communes/les_rues_des_vignes/aide_permis.py
openfisca_france_local/communes/montpellier/eligibilite.py
openfisca_france_local/communes/montpellier/montpellier_mutuelle_communale.py
openfisca_france_local/communes/nantes/aide_carte_blanche.py
openfisca_france_local/communes/saint_louis/eligibilite.py
openfisca_france_local/departements/cotes_d_armor/eligibilite.py
openfisca_france_local/departements/cotes_d_armor/fonds_solidarite_logement/acces_maintien.py
openfisca_france_local/departements/cotes_d_armor/fonds_solidarite_logement/assurance_locative_energie.py
openfisca_france_local/departements/cotes_d_armor/fonds_solidarite_logement/base_ressource.py
openfisca_france_local-6.17.10.dist-info/licenses/LICENSE
openfisca_france_local-6.17.10.dist-info/METADATA
openfisca_france_local-6.17.10.dist-info/WHEEL
openfisca_france_local-6.17.10.dist-info/top_level.txt
openfisca_france_local-6.17.10.dist-info/RECORD
