Metadata-Version: 2.4
Name: OpenFisca-France-Local
Version: 6.17.10
Summary: Extension OpenFisca pour nos partenariats avec les collectivités territoriales
Home-page: https://github.com/openfisca/openfisca-france-local
Author: OpenFisca Team
Author-email: contact@openfisca.fr
License: http://www.fsf.org/licensing/licenses/agpl-3.0.html
Keywords: benefit france france-local microsimulation social tax
Classifier: Development Status :: 5 - Production/Stable
Classifier: License :: OSI Approved :: GNU Affero General Public License v3
Classifier: Operating System :: POSIX
Classifier: Programming Language :: Python
Classifier: Programming Language :: Python :: 3.9
Classifier: Programming Language :: Python :: 3.10
Classifier: Programming Language :: Python :: 3.11
Classifier: Topic :: Scientific/Engineering :: Information Analysis
License-File: LICENSE
Requires-Dist: OpenFisca-Core<45,>=43
Requires-Dist: OpenFisca-France<176.0.0,>=169.0.0
Requires-Dist: pandas<2.0,>=1.5.3
Provides-Extra: test
Requires-Dist: nose; extra == "test"
Provides-Extra: excel-reader
Requires-Dist: openpyxl==3.1.2; extra == "excel-reader"
Dynamic: author
Dynamic: author-email
Dynamic: classifier
Dynamic: description-content-type
Dynamic: home-page
Dynamic: keywords
Dynamic: license
Dynamic: license-file
Dynamic: provides-extra
Dynamic: requires-dist
Dynamic: summary
